MANIFEST.in
README.rst
setup.py
growai/__init__.py
growai/grow.py
growai.egg-info/PKG-INFO
growai.egg-info/SOURCES.txt
growai.egg-info/dependency_links.txt
growai.egg-info/requires.txt
growai.egg-info/top_level.txt
growai/analysis/__init__.py
growai/analysis/analise.py
growai/analysis/chemical_space.py
growai/analysis/drug_like.py
growai/analysis/helpers.py
growai/analysis/molecule.py
growai/analysis/plot_fragments.py
growai/analysis/validity.py
growai/constants/__init__.py
growai/constants/constants.py
growai/model/__init__.py
growai/model/docking/__init__.py
growai/model/docking/analyse_glide.py
growai/model/docking/glide.py
growai/model/helpers/__init__.py
growai/model/helpers/formats.py
growai/model/helpers/helpers.py
growai/model/weights/__init__.py
growai/model/weights/final_subset_cpu.hdf5