Metadata-Version: 1.1
Name: growai
Version: 1.0.0
Summary: Coupling active learning approaches with generative models to automatically generate and rank 1M compounds.
Home-page: https://github.com/nostrumbiodiscovery/growai
Author: Daniel Soler
Author-email: daniel.soler@nostrumbiodiscovery.com
License: UNKNOWN
Platform: UNKNOWN
Classifier: Programming Language :: Python :: 3
Classifier: License :: OSI Approved :: MIT License
Classifier: Operating System :: OS Independent
